py_bls_api/__init__.py
py_bls_api/bls_api.py
py_bls_api-0.1.2.dist-info/licenses/LICENSE
py_bls_api-0.1.2.dist-info/METADATA
py_bls_api-0.1.2.dist-info/WHEEL
py_bls_api-0.1.2.dist-info/top_level.txt
py_bls_api-0.1.2.dist-info/RECORD
