Metadata-Version: 2.4
Name: py-bls-api
Version: 0.1.2
Summary: A Python wrapper for the U.S. Bureau of Labor Statistics (BLS) API
Author: Christopher Morris
Classifier: Programming Language :: Python :: 3
Classifier: Operating System :: OS Independent
Requires-Python: >=3.6
License-File: LICENSE
Requires-Dist: pandas>=1.3.0
Requires-Dist: requests>=2.25.0
Dynamic: license-file
